{
  "sessions": [],
  "drivers": [
    {
      "id": "1729719141784",
      "name": "Alice",
      "cars": [
        {
          "id": "1729719280813",
          "name": "SC10 Pro2"
        },
        {
          "id": "1729719287450",
          "name": "SC10 Pro4"
        }
      ]
    },
    {
      "id": "1729719292587",
      "name": "Bob",
      "cars": [
        {
          "id": "1729719299126",
          "name": "Slash 2wd"
        },
        {
          "id": "1729719307925",
          "name": "Slash 4x4"
        }
      ]
    }
  ],
  "lastUpdated": "2024-10-23T21:39:46.780Z"
}